zyank/__init__.py
zyank/parser.py
zyank-0.10.1.dist-info/METADATA
zyank-0.10.1.dist-info/WHEEL
zyank-0.10.1.dist-info/licenses/LICENSE
zyank-0.10.1.dist-info/RECORD
