Metadata-Version: 2.4
Name: zyank
Version: 0.10.1
Summary: library for adding basic functions for collecting data from the cian website
Author-email: Void Hiko <racomarov@gmail.com>
License-File: LICENSE
Classifier: License :: OSI Approved :: MIT License
Classifier: Operating System :: OS Independent
Classifier: Programming Language :: Python :: 3
Requires-Python: >=3.10.0
